<UgUiFile xmlns:i="http://www.w3.org/2001/XMLSchema-instance" xmlns="http://schemas.datacontract.org/2004/07/Ujeby.UgUi.Core"><Connections><UgUiFile.Connection><LeftAnchorName>OutputAnchorValue</LeftAnchorName><LeftId>f76ac854-6575-4480-8466-7c344cfe8b56</LeftId><RightAnchorName>InputAnchorSeed</RightAnchorName><RightId>f0b4deb2-132c-4a4c-89e0-84c6cb730001</RightId></UgUiFile.Connection><UgUiFile.Connection><LeftAnchorName>OutputAnchorValue</LeftAnchorName><LeftId>a84028d7-5063-44d9-aff4-40bd7180d29b</LeftId><RightAnchorName>InputAnchorLength</RightAnchorName><RightId>b5df8463-6a07-4e99-b118-23ffff539d17</RightId></UgUiFile.Connection><UgUiFile.Connection><LeftAnchorName>OutputAnchorValue</LeftAnchorName><LeftId>f0b4deb2-132c-4a4c-89e0-84c6cb730001</LeftId><RightAnchorName>InputAnchorX</RightAnchorName><RightId>a38cdbf7-485a-4b4c-9413-8023b48790bc</RightId></UgUiFile.Connection></Connections><Nodes><UgUiFile.Node><Data>{"Format":"yyyyMMdd_HHmmssfff"}</Data><Id>1e980b92-fe01-4b60-a72e-924cd7b63816</Id><Name /><Position xmlns:d4p1="http://schemas.datacontract.org/2004/07/System.Windows"><d4p1:_x>292</d4p1:_x><d4p1:_y>237</d4p1:_y></Position><TypeName>Ujeby.UgUi.Nodes.Generators._DateTime</TypeName></UgUiFile.Node><UgUiFile.Node><Data>{"From":"1","To":"16"}</Data><Id>a84028d7-5063-44d9-aff4-40bd7180d29b</Id><Name /><Position xmlns:d4p1="http://schemas.datacontract.org/2004/07/System.Windows"><d4p1:_x>570</d4p1:_x><d4p1:_y>317</d4p1:_y></Position><TypeName>Ujeby.UgUi.Nodes.Generators.For</TypeName></UgUiFile.Node><UgUiFile.Node><Data>{}</Data><Id>f76ac854-6575-4480-8466-7c344cfe8b56</Id><Name /><Position xmlns:d4p1="http://schemas.datacontract.org/2004/07/System.Windows"><d4p1:_x>265</d4p1:_x><d4p1:_y>95</d4p1:_y></Position><TypeName>Ujeby.UgUi.Nodes.Generators._Guid</TypeName></UgUiFile.Node><UgUiFile.Node><Data>{"Length":"3"}</Data><Id>b5df8463-6a07-4e99-b118-23ffff539d17</Id><Name /><Position xmlns:d4p1="http://schemas.datacontract.org/2004/07/System.Windows"><d4p1:_x>827</d4p1:_x><d4p1:_y>281</d4p1:_y></Position><TypeName>Ujeby.UgUi.Nodes.Generators.RandomString</TypeName></UgUiFile.Node><UgUiFile.Node><Data>{"Seed":"e941a517-5abb-4123-afb2-bc14fa92e78e"}</Data><Id>f0b4deb2-132c-4a4c-89e0-84c6cb730001</Id><Name /><Position xmlns:d4p1="http://schemas.datacontract.org/2004/07/System.Windows"><d4p1:_x>646</d4p1:_x><d4p1:_y>131</d4p1:_y></Position><TypeName>Ujeby.UgUi.Nodes.Generators.Rng</TypeName></UgUiFile.Node><UgUiFile.Node><Data>{"X":"0,469574232804391"}</Data><Id>a38cdbf7-485a-4b4c-9413-8023b48790bc</Id><Name /><Position xmlns:d4p1="http://schemas.datacontract.org/2004/07/System.Windows"><d4p1:_x>1024</d4p1:_x><d4p1:_y>170</d4p1:_y></Position><TypeName>Ujeby.UgUi.Nodes.Types.Double</TypeName></UgUiFile.Node></Nodes></UgUiFile>